[
  {
    "name": "Spicy McCrispy",
    "favorite": "false"
  },
  {
    "name": "Big Mac",
    "favorite": "false"
  },
  {
    "name": "Chicken Nuggets",
    "favorite": "false"
  },
  {
    "name": "Big Burger",
    "favorite": "false"
  },
  {
    "name": "Big Burger",
    "favorite": "false"
  },
  {
    "name": "Big Burger",
    "favorite": "false"
  },
  {
    "name": "Big Burger",
    "favorite": "false"
  },
  {
    "name": "Big Burger",
    "favorite": "false"
  },
  {
    "name": "Big Burger",
    "favorite": "false"
  },
  {
    "name": "Big Burger",
    "favorite": "false"
  }
]
